cat_reporting_specs/__init__.py
cat_reporting_specs/events.py
cat_reporting_specs/include_key.py
cat_reporting_specs/linkage_keys.py
cat_reporting_specs/types.py
cat_reporting_specs-0.0.3.dist-info/AUTHORS.rst
cat_reporting_specs-0.0.3.dist-info/LICENSE
cat_reporting_specs-0.0.3.dist-info/LICENSE.txt
cat_reporting_specs-0.0.3.dist-info/METADATA
cat_reporting_specs-0.0.3.dist-info/WHEEL
cat_reporting_specs-0.0.3.dist-info/top_level.txt
cat_reporting_specs-0.0.3.dist-info/RECORD
